onnxstream/__init__.py
onnxstream-0.0.1.dev0.dist-info/METADATA
onnxstream-0.0.1.dev0.dist-info/WHEEL
onnxstream-0.0.1.dev0.dist-info/top_level.txt
onnxstream-0.0.1.dev0.dist-info/RECORD
